Illuminate/Auth/Access/Gate.py
Illuminate/Auth/Access/__init__.py
Illuminate/Auth/AuthServiceProvider.py
Illuminate/Auth/Middleware/Authenticate.py
Illuminate/Auth/Middleware/__init__.py
Illuminate/Auth/__init__.py
Illuminate/Collections/Arr.py
Illuminate/Collections/Collection.py
Illuminate/Collections/Enumerable.py
Illuminate/Collections/Traits/EnumeratesValues.py
Illuminate/Collections/Traits/__init__.py
Illuminate/Collections/__init__.py
Illuminate/Collections/helpers.py
Illuminate/Conditionable/Conditionable.py
Illuminate/Conditionable/__init__.py
Illuminate/Config/Repository.py
Illuminate/Config/__init__.py
Illuminate/Container/Container.py
Illuminate/Container/__init__.py
Illuminate/Contracts/Auth/Access/Gate.py
Illuminate/Contracts/Auth/Access/__init__.py
Illuminate/Contracts/Collections/Collection.py
Illuminate/Contracts/Collections/__init__.py
Illuminate/Contracts/Container/Container.py
Illuminate/Contracts/Container/__init__.py
Illuminate/Contracts/Debug/ExceptionHandler.py
Illuminate/Contracts/Debug/__init__.py
Illuminate/Contracts/Events/Dispatcher.py
Illuminate/Contracts/Events/__init__.py
Illuminate/Contracts/Foundation/Application.py
Illuminate/Contracts/Foundation/Console/Applicatiton.py
Illuminate/Contracts/Foundation/Console/Kernel.py
Illuminate/Contracts/Foundation/__init__.py
Illuminate/Contracts/Http/Kernel.py
Illuminate/Contracts/Http/Request.py
Illuminate/Contracts/Http/Response.py
Illuminate/Contracts/Http/__init__.py
Illuminate/Contracts/Resolvable.py
Illuminate/Contracts/Routing/Router.py
Illuminate/Contracts/Routing/__init__.py
Illuminate/Contracts/Support/JsonSerializable.py
Illuminate/Contracts/Support/ServiceProvider.py
Illuminate/Contracts/Support/__init__.py
Illuminate/Contracts/__init__.py
Illuminate/Database/Serializable.py
Illuminate/Database/__init__.py
Illuminate/Events/Dispatcher.py
Illuminate/Events/EventServiceProvider.py
Illuminate/Events/__init__.py
Illuminate/Exceptions/Handler.py
pyjinx-0.2.4.dist-info/LICENSE.md
pyjinx-0.2.4.dist-info/METADATA
pyjinx-0.2.4.dist-info/WHEEL
pyjinx-0.2.4.dist-info/RECORD
